{"name": " ", "children": [{"name": "南风", "children": [{"name": "优", "size": 9306}, {"name": "良", "size": 2490}, {"name": "轻度污染", "size": 516}, {"name": "中度污染", "size": 170}, {"name": "重度污染", "size": 48}]}, {"name": "西南风", "children": [{"name": "优", "size": 31784}, {"name": "良", "size": 1610}, {"name": "轻度污染", "size": 90}, {"name": "中度污染", "size": 2}]}, {"name": "西风", "children": [{"name": "优", "size": 11177}, {"name": "良", "size": 1118}, {"name": "轻度污染", "size": 44}, {"name": "中度污染", "size": 2}]}, {"name": "西北风", "children": [{"name": "优", "size": 3928}, {"name": "良", "size": 1229}, {"name": "轻度污染", "size": 190}, {"name": "中度污染", "size": 29}, {"name": "重度污染", "size": 1}]}, {"name": "北风", "children": [{"name": "优", "size": 5912}, {"name": "良", "size": 2573}, {"name": "轻度污染", "size": 326}, {"name": "中度污染", "size": 75}, {"name": "重度污染", "size": 31}]}, {"name": "东北风", "children": [{"name": "优", "size": 1568}, {"name": "良", "size": 992}, {"name": "轻度污染", "size": 36}, {"name": "中度污染", "size": 3}]}, {"name": "东风", "children": [{"name": "优", "size": 6942}, {"name": "良", "size": 993}, {"name": "轻度污染", "size": 32}, {"name": "中度污染", "size": 4}]}, {"name": "东南风", "children": [{"name": "优", "size": 6118}, {"name": "良", "size": 1958}, {"name": "轻度污染", "size": 299}, {"name": "中度污染", "size": 15}, {"name": "重度污染", "size": 4}]}]}
