{"name": " ", "children": [{"name": "南风", "children": [{"name": "良", "size": 1500}, {"name": "优", "size": 723}, {"name": "轻度污染", "size": 462}, {"name": "中度污染", "size": 164}, {"name": "重度污染", "size": 145}, {"name": "严重污染", "size": 10}]}, {"name": "西南风", "children": [{"name": "良", "size": 1324}, {"name": "轻度污染", "size": 454}, {"name": "优", "size": 192}, {"name": "重度污染", "size": 176}, {"name": "中度污染", "size": 112}, {"name": "严重污染", "size": 12}]}, {"name": "西风", "children": [{"name": "良", "size": 1924}, {"name": "优", "size": 430}, {"name": "轻度污染", "size": 384}, {"name": "中度污染", "size": 43}, {"name": "严重污染", "size": 34}, {"name": "重度污染", "size": 33}]}, {"name": "西北风", "children": [{"name": "良", "size": 3958}, {"name": "优", "size": 1316}, {"name": "轻度污染", "size": 787}, {"name": "中度污染", "size": 270}, {"name": "重度污染", "size": 166}, {"name": "严重污染", "size": 33}]}, {"name": "北风", "children": [{"name": "良", "size": 2214}, {"name": "优", "size": 771}, {"name": "轻度污染", "size": 590}, {"name": "中度污染", "size": 301}, {"name": "重度污染", "size": 91}, {"name": "严重污染", "size": 14}]}, {"name": "东北风", "children": [{"name": "良", "size": 1087}, {"name": "优", "size": 699}, {"name": "轻度污染", "size": 367}, {"name": "中度污染", "size": 102}, {"name": "严重污染", "size": 33}, {"name": "重度污染", "size": 30}]}, {"name": "东风", "children": [{"name": "良", "size": 1429}, {"name": "轻度污染", "size": 318}, {"name": "优", "size": 311}, {"name": "中度污染", "size": 44}, {"name": "严重污染", "size": 25}, {"name": "重度污染", "size": 15}]}, {"name": "东南风", "children": [{"name": "优", "size": 2062}, {"name": "良", "size": 1134}, {"name": "轻度污染", "size": 334}, {"name": "中度污染", "size": 17}, {"name": "重度污染", "size": 5}]}]}
