{"name": " ", "children": [{"name": "南风", "children": [{"name": "优", "size": 2855}, {"name": "良", "size": 2090}, {"name": "轻度污染", "size": 293}, {"name": "中度污染", "size": 54}, {"name": "重度污染", "size": 7}]}, {"name": "西南风", "children": [{"name": "良", "size": 299}, {"name": "优", "size": 123}, {"name": "轻度污染", "size": 35}, {"name": "中度污染", "size": 19}]}, {"name": "西风", "children": [{"name": "良", "size": 1741}, {"name": "轻度污染", "size": 581}, {"name": "优", "size": 388}, {"name": "中度污染", "size": 119}, {"name": "重度污染", "size": 19}]}, {"name": "西北风", "children": [{"name": "良", "size": 10705}, {"name": "轻度污染", "size": 5412}, {"name": "优", "size": 1868}, {"name": "中度污染", "size": 1560}, {"name": "重度污染", "size": 640}]}, {"name": "北风", "children": [{"name": "良", "size": 3133}, {"name": "优", "size": 2357}, {"name": "轻度污染", "size": 869}, {"name": "中度污染", "size": 273}, {"name": "重度污染", "size": 60}]}, {"name": "东北风", "children": [{"name": "良", "size": 1665}, {"name": "优", "size": 1606}, {"name": "轻度污染", "size": 426}, {"name": "中度污染", "size": 54}, {"name": "重度污染", "size": 2}]}, {"name": "东风", "children": [{"name": "良", "size": 994}, {"name": "优", "size": 464}, {"name": "轻度污染", "size": 316}, {"name": "中度污染", "size": 39}, {"name": "重度污染", "size": 3}]}, {"name": "东南风", "children": [{"name": "优", "size": 1922}, {"name": "良", "size": 1771}, {"name": "轻度污染", "size": 101}, {"name": "中度污染", "size": 31}, {"name": "重度污染", "size": 1}]}]}
