{"name": " ", "children": [{"name": "南风", "children": [{"name": "良", "size": 2545}, {"name": "优", "size": 2313}, {"name": "轻度污染", "size": 302}, {"name": "中度污染", "size": 44}, {"name": "重度污染", "size": 32}]}, {"name": "西南风", "children": [{"name": "优", "size": 1969}, {"name": "良", "size": 1272}, {"name": "轻度污染", "size": 147}, {"name": "重度污染", "size": 41}, {"name": "中度污染", "size": 25}]}, {"name": "西风", "children": [{"name": "优", "size": 697}, {"name": "良", "size": 544}, {"name": "轻度污染", "size": 110}, {"name": "中度污染", "size": 17}, {"name": "重度污染", "size": 8}]}, {"name": "西北风", "children": [{"name": "优", "size": 1238}, {"name": "良", "size": 979}, {"name": "轻度污染", "size": 124}, {"name": "中度污染", "size": 22}, {"name": "重度污染", "size": 11}]}, {"name": "北风", "children": [{"name": "良", "size": 2336}, {"name": "优", "size": 2030}, {"name": "轻度污染", "size": 321}, {"name": "中度污染", "size": 65}, {"name": "重度污染", "size": 44}]}, {"name": "东北风", "children": [{"name": "良", "size": 975}, {"name": "优", "size": 512}, {"name": "轻度污染", "size": 179}, {"name": "中度污染", "size": 21}, {"name": "重度污染", "size": 6}]}, {"name": "东风", "children": [{"name": "良", "size": 590}, {"name": "优", "size": 447}, {"name": "轻度污染", "size": 157}, {"name": "中度污染", "size": 17}, {"name": "重度污染", "size": 3}]}, {"name": "东南风", "children": [{"name": "良", "size": 1693}, {"name": "优", "size": 787}, {"name": "轻度污染", "size": 342}, {"name": "中度污染", "size": 23}, {"name": "重度污染", "size": 7}]}]}
