{"name": " ", "children": [{"name": "南风", "children": [{"name": "良", "size": 3521}, {"name": "优", "size": 3265}, {"name": "轻度污染", "size": 618}, {"name": "中度污染", "size": 61}, {"name": "重度污染", "size": 16}]}, {"name": "西南风", "children": [{"name": "优", "size": 4260}, {"name": "良", "size": 2322}, {"name": "轻度污染", "size": 398}, {"name": "中度污染", "size": 39}, {"name": "重度污染", "size": 16}]}, {"name": "西风", "children": [{"name": "良", "size": 1115}, {"name": "优", "size": 833}, {"name": "轻度污染", "size": 148}, {"name": "中度污染", "size": 54}, {"name": "重度污染", "size": 19}]}, {"name": "西北风", "children": [{"name": "良", "size": 950}, {"name": "优", "size": 729}, {"name": "轻度污染", "size": 167}, {"name": "中度污染", "size": 26}, {"name": "重度污染", "size": 19}]}, {"name": "北风", "children": [{"name": "良", "size": 2063}, {"name": "优", "size": 1695}, {"name": "轻度污染", "size": 276}, {"name": "中度污染", "size": 40}, {"name": "重度污染", "size": 24}]}, {"name": "东北风", "children": [{"name": "良", "size": 656}, {"name": "优", "size": 230}, {"name": "轻度污染", "size": 102}, {"name": "重度污染", "size": 7}, {"name": "中度污染", "size": 6}]}, {"name": "东风", "children": [{"name": "良", "size": 935}, {"name": "优", "size": 648}, {"name": "轻度污染", "size": 169}, {"name": "中度污染", "size": 72}, {"name": "重度污染", "size": 14}]}, {"name": "东南风", "children": [{"name": "良", "size": 4156}, {"name": "轻度污染", "size": 1512}, {"name": "优", "size": 807}, {"name": "中度污染", "size": 374}, {"name": "重度污染", "size": 123}]}]}
