{"name": " ", "children": [{"name": "南风", "children": [{"name": "良", "size": 2716}, {"name": "优", "size": 2648}, {"name": "轻度污染", "size": 784}, {"name": "中度污染", "size": 279}, {"name": "重度污染", "size": 233}, {"name": "严重污染", "size": 33}]}, {"name": "西南风", "children": [{"name": "优", "size": 6003}, {"name": "良", "size": 1532}, {"name": "轻度污染", "size": 420}, {"name": "中度污染", "size": 21}, {"name": "重度污染", "size": 6}, {"name": "严重污染", "size": 1}]}, {"name": "西风", "children": [{"name": "优", "size": 2874}, {"name": "良", "size": 916}, {"name": "轻度污染", "size": 164}, {"name": "中度污染", "size": 44}, {"name": "重度污染", "size": 2}]}, {"name": "西北风", "children": [{"name": "优", "size": 1512}, {"name": "良", "size": 622}, {"name": "轻度污染", "size": 231}, {"name": "中度污染", "size": 7}, {"name": "重度污染", "size": 2}]}, {"name": "北风", "children": [{"name": "优", "size": 1938}, {"name": "良", "size": 1784}, {"name": "轻度污染", "size": 458}, {"name": "中度污染", "size": 104}, {"name": "重度污染", "size": 42}]}, {"name": "东北风", "children": [{"name": "优", "size": 1198}, {"name": "良", "size": 1052}, {"name": "轻度污染", "size": 271}, {"name": "重度污染", "size": 62}, {"name": "中度污染", "size": 44}]}, {"name": "东风", "children": [{"name": "优", "size": 2101}, {"name": "良", "size": 794}, {"name": "轻度污染", "size": 104}, {"name": "重度污染", "size": 28}, {"name": "中度污染", "size": 24}]}, {"name": "东南风", "children": [{"name": "优", "size": 2465}, {"name": "良", "size": 1986}, {"name": "轻度污染", "size": 471}, {"name": "中度污染", "size": 82}, {"name": "重度污染", "size": 77}]}]}
